ultraheat_api/__init__.py
ultraheat_api/const.py
ultraheat_api/file_reader.py
ultraheat_api/find_ports.py
ultraheat_api/response.py
ultraheat_api/service.py
ultraheat_api/ultraheat_reader.py
ultraheat_api-0.5.7.dist-info/LICENCE
ultraheat_api-0.5.7.dist-info/METADATA
ultraheat_api-0.5.7.dist-info/WHEEL
ultraheat_api-0.5.7.dist-info/top_level.txt
ultraheat_api-0.5.7.dist-info/RECORD
