Metadata-Version: 2.1
Name: ultraheat-api
Version: 0.5.7
Summary: Reading usage data from the Landys & Gyr Ultraheat heat meter unit
Home-page: https://github.com/vpathuis/ultraheat
Author: vpathuis
License: MIT
License-File: LICENCE
Requires-Dist: pyserial
